sotrace/__init__.py
sotrace/__main__.py
sotrace/sotrace.py
sotrace-1.1.2.dist-info/METADATA
sotrace-1.1.2.dist-info/WHEEL
sotrace-1.1.2.dist-info/top_level.txt
sotrace-1.1.2.dist-info/RECORD
