Metadata-Version: 2.1
Name: sotrace
Version: 1.1.2
Summary: Get and open StackOverflow posts for your tracebacks.
Home-page: https://github.com/SuperMaZingCoder/sotrace
Author: SuperMaZingCoder
Author-email: supermazingcoder@gmail.com
License: MIT
Platform: UNKNOWN
Classifier: License :: OSI Approved :: MIT License
Classifier: Programming Language :: Python :: 3
Requires-Python: >=3.5.0
Requires-Dist: requests (>=2.22.0)
Requires-Dist: rich (>=9.4.0)
